.gitignore
.travis.yml
MANIFEST.in
Makefile
README.md
requirements.txt
setup.py
tox.ini
cronredux/__init__.py
cronredux/cronparser.py
cronredux/main.py
cronredux/notification.py
cronredux/scheduler.py
cronredux.egg-info/PKG-INFO
cronredux.egg-info/SOURCES.txt
cronredux.egg-info/dependency_links.txt
cronredux.egg-info/entry_points.txt
cronredux.egg-info/requires.txt
cronredux.egg-info/top_level.txt
cronredux/diag/__init__.py
cronredux/diag/web.py
cronredux/diag/ui/index.html
cronredux/diag/ui/task.html
cronredux/diag/ui/task_exec.html
cronredux/diag/ui/static/theme.css
test/__init__.py
test/cronparser.py
test/scheduler.py