Metadata-Version: 1.1
Name: cronredux
Version: 2.7.2
Summary: A reimagined cron executor
Home-page: https://github.com/homecu/cronredux/
Author: HomeCU
Author-email: developers@homecu.com
License: MIT
Platform: UNKNOWN
Classifier: Development Status :: 4 - Beta
Classifier: Intended Audience :: Developers
Classifier: License :: OSI Approved :: MIT License
Classifier: Operating System :: OS Independent
Classifier: Programming Language :: Python
Classifier: Programming Language :: Python :: 3.4
Classifier: Programming Language :: Python :: 3.5
